<batchVoucher>
  <id>cb7592ae-621c-4f35-bc1d-47909e55f9f5</id>
  <batchGroup>Amherst College (AC)</batchGroup>
  <created>2019-12-07T00:01:04Z</created>
  <start>2019-12-06T00:00:00Z</start>
  <end>2019-12-07T00:00:00Z</end>
  <batchedVouchers>
    <batchedVoucher>
      <accountingCode>0206</accountingCode>
      <amount>23.45</amount>
      <batchedVoucherLines>
        <batchedVoucherLine>
          <amount>23.45</amount>
          <fundCodes>
            <fundCode>HIST</fundCode>
            <fundCode>LATHIST</fundCode>
            <fundCode>CANHIST</fundCode>
          </fundCodes>
          <externalAccountNumber>54321098</externalAccountNumber>
        </batchedVoucherLine>
      </batchedVoucherLines>
      <adjustments>
        <adjustment>
          <description>GST</description>
          <prorate>Not pro rate</prorate>
          <relationToTotal>Separate from</relationToTotal>
          <type>Payment</type>
          <value>20.0</value>
          <totalAmount>20.0</totalAmount>
        </adjustment>
      </adjustments>
      <disbursementNumber>EFT546789</disbursementNumber>
      <disbursementDate>2019-12-06T00:01:04Z</disbursementDate>
      <disbursementAmount>23.45</disbursementAmount>
      <enclosureNeeded>false</enclosureNeeded>
      <exchangeRate>1</exchangeRate>
      <folioInvoiceNo>123folionumber456</folioInvoiceNo>
      <invoiceCurrency>USD</invoiceCurrency>
      <invoiceDate>2019-12-05T00:00:00Z</invoiceDate>
      <invoiceTerms>Payment in Advance</invoiceTerms>
      <invoiceNote>Process immediately</invoiceNote>
      <status>Paid</status>
      <systemCurrency>USD</systemCurrency>
      <type>Voucher</type>
      <vendorInvoiceNo>YK75851</vendorInvoiceNo>
      <vendorName>GOBI</vendorName>
      <voucherDate>2019-12-06T00:00:00Z</voucherDate>
      <voucherNumber>1023</voucherNumber>
      <vendorAddress>
        <addressLine1>10 Estes Street</addressLine1>
        <city>Ipswich</city>
        <stateRegion>MA</stateRegion>
        <zipCode>01938</zipCode>
        <country>USA</country>
      </vendorAddress>
    </batchedVoucher>
  </batchedVouchers>
  <totalRecords>1</totalRecords>
</batchVoucher>
